mds_array_manipulation/__init__.py
mds_array_manipulation/argmax.py
mds_array_manipulation/count_nonzero_elements.py
mds_array_manipulation/search_array.py
mds_array_manipulation/sort_array.py
mds_array_manipulation-0.0.10.dist-info/LICENSE
mds_array_manipulation-0.0.10.dist-info/METADATA
mds_array_manipulation-0.0.10.dist-info/WHEEL
mds_array_manipulation-0.0.10.dist-info/RECORD
